dedupe/variables/__init__.py
dedupe/variables/number.py
dedupe_variable_number-0.0.1.dist-info/METADATA
dedupe_variable_number-0.0.1.dist-info/WHEEL
dedupe_variable_number-0.0.1.dist-info/top_level.txt
dedupe_variable_number-0.0.1.dist-info/RECORD
