Metadata-Version: 2.1
Name: dedupe-variable-number
Version: 0.0.1
Summary: Employer variable type for dedupe
Home-page: https://github.com/dedupeio/dedupe-variable-number
Author: UNKNOWN
Author-email: UNKNOWN
License: The MIT License: http://www.opensource.org/licenses/mit-license.php
Platform: UNKNOWN
Requires-Dist: dedupe
